{
  "$schema": "https://developer.microsoft.com/json-schemas/fabric/item/report/definition/visualContainer/2.9.0/schema.json",
  "name": "53dc7c57fa52db001299",
  "position": {
    "x": 976,
    "y": 280,
    "z": 5,
    "height": 320,
    "width": 912,
    "tabOrder": 5
  },
  "visual": {
    "visualType": "textbox",
    "objects": {
      "general": [
        {
          "properties": {
            "paragraphs": [
              {
                "textRuns": [
                  {
                    "value": "Scope & refresh",
                    "textStyle": {
                      "fontFamily": "Segoe UI Semibold",
                      "fontSize": "14pt",
                      "color": "#0F1C24",
                      "fontWeight": "bold"
                    }
                  }
                ],
                "horizontalTextAlignment": "left"
              },
              {
                "textRuns": [
                  {
                    "value": "RSI Signal Desk is rules-based (RSI ≤30 Long / ≥70 Short) with next-day hit rates — not an ML forecast.",
                    "textStyle": {
                      "fontFamily": "Segoe UI",
                      "fontSize": "12pt",
                      "color": "#0F1C24"
                    }
                  }
                ],
                "horizontalTextAlignment": "left"
              },
              {
                "textRuns": [
                  {
                    "value": "Not investment advice — portfolio demonstration only.",
                    "textStyle": {
                      "fontFamily": "Segoe UI",
                      "fontSize": "12pt",
                      "color": "#0F1C24"
                    }
                  }
                ],
                "horizontalTextAlignment": "left"
              },
              {
                "textRuns": [
                  {
                    "value": "Refresh gold data: node scripts/build-gold.mjs — then refresh the semantic model in Desktop.",
                    "textStyle": {
                      "fontFamily": "Segoe UI",
                      "fontSize": "12pt",
                      "color": "#0F1C24"
                    }
                  }
                ],
                "horizontalTextAlignment": "left"
              }
            ]
          }
        }
      ]
    },
    "visualContainerObjects": {
      "background": [
        {
          "properties": {
            "show": {
              "expr": {
                "Literal": {
                  "Value": "false"
                }
              }
            }
          }
        }
      ],
      "border": [
        {
          "properties": {
            "show": {
              "expr": {
                "Literal": {
                  "Value": "false"
                }
              }
            }
          }
        }
      ],
      "padding": [
        {
          "properties": {
            "top": {
              "expr": {
                "Literal": {
                  "Value": "0D"
                }
              }
            },
            "bottom": {
              "expr": {
                "Literal": {
                  "Value": "0D"
                }
              }
            },
            "left": {
              "expr": {
                "Literal": {
                  "Value": "0D"
                }
              }
            },
            "right": {
              "expr": {
                "Literal": {
                  "Value": "0D"
                }
              }
            }
          }
        }
      ],
      "visualHeader": [
        {
          "properties": {
            "show": {
              "expr": {
                "Literal": {
                  "Value": "false"
                }
              }
            }
          }
        }
      ]
    }
  }
}