{
  "$schema": "https://developer.microsoft.com/json-schemas/fabric/item/report/definition/visualContainer/2.9.0/schema.json",
  "name": "bb2102f11522790bfe71",
  "position": {
    "x": 1300,
    "y": 112,
    "z": 7,
    "height": 896,
    "width": 588,
    "tabOrder": 7
  },
  "visual": {
    "visualType": "iconMapV34089C0EB522B416294AA926F71B4FDBB",
    "query": {
      "queryState": {
        "category": {
          "projections": [
            {
              "field": {
                "Column": {
                  "Expression": {
                    "SourceRef": {
                      "Entity": "DimCustomer"
                    }
                  },
                  "Property": "City"
                }
              },
              "queryRef": "DimCustomer.City",
              "nativeQueryRef": "City",
              "active": true
            }
          ]
        },
        "Longitude": {
          "projections": [
            {
              "field": {
                "Aggregation": {
                  "Expression": {
                    "Column": {
                      "Expression": {
                        "SourceRef": {
                          "Entity": "DimCustomer"
                        }
                      },
                      "Property": "Longitude"
                    }
                  },
                  "Function": 1
                }
              },
              "queryRef": "Avg(DimCustomer.Longitude)",
              "nativeQueryRef": "Average of Longitude"
            }
          ]
        },
        "Latitude": {
          "projections": [
            {
              "field": {
                "Aggregation": {
                  "Expression": {
                    "Column": {
                      "Expression": {
                        "SourceRef": {
                          "Entity": "DimCustomer"
                        }
                      },
                      "Property": "Latitude"
                    }
                  },
                  "Function": 1
                }
              },
              "queryRef": "Avg(DimCustomer.Latitude)",
              "nativeQueryRef": "Average of Latitude"
            }
          ]
        },
        "Size": {
          "projections": [
            {
              "field": {
                "Measure": {
                  "Expression": {
                    "SourceRef": {
                      "Entity": "DimCustomer"
                    }
                  },
                  "Property": "Customer Base"
                }
              },
              "queryRef": "DimCustomer.Customer Base",
              "nativeQueryRef": "Customer Base"
            }
          ]
        }
      }
    },
    "objects": {
      "mapLayers": [
        {
          "properties": {
            "backgroundMapLayer": {
              "expr": {
                "Literal": {
                  "Value": "'OpenTopoMap'"
                }
              }
            }
          }
        }
      ],
      "zoom": [
        {
          "properties": {
            "defaultLatitude": {
              "expr": {
                "Literal": {
                  "Value": "9L"
                }
              }
            },
            "defaultLongitude": {
              "expr": {
                "Literal": {
                  "Value": "8L"
                }
              }
            },
            "defaultZoom": {
              "expr": {
                "Literal": {
                  "Value": "5.5D"
                }
              }
            },
            "zoomOnSingleItem": {
              "expr": {
                "Literal": {
                  "Value": "true"
                }
              }
            },
            "includeInZoom": {
              "expr": {
                "Literal": {
                  "Value": "'Yes'"
                }
              }
            }
          }
        }
      ],
      "circles": [
        {
          "properties": {
            "minSize": {
              "expr": {
                "Literal": {
                  "Value": "8L"
                }
              }
            },
            "maxSize": {
              "expr": {
                "Literal": {
                  "Value": "28L"
                }
              }
            }
          }
        }
      ],
      "controls": [
        {
          "properties": {
            "zoom": {
              "expr": {
                "Literal": {
                  "Value": "true"
                }
              }
            }
          }
        }
      ]
    },
    "visualContainerObjects": {
      "background": [
        {
          "properties": {
            "show": {
              "expr": {
                "Literal": {
                  "Value": "true"
                }
              }
            },
            "color": {
              "solid": {
                "color": {
                  "expr": {
                    "Literal": {
                      "Value": "'#FFFFFF'"
                    }
                  }
                }
              }
            },
            "transparency": {
              "expr": {
                "Literal": {
                  "Value": "0D"
                }
              }
            }
          }
        }
      ],
      "border": [
        {
          "properties": {
            "show": {
              "expr": {
                "Literal": {
                  "Value": "true"
                }
              }
            },
            "color": {
              "solid": {
                "color": {
                  "expr": {
                    "Literal": {
                      "Value": "'#E8EEF2'"
                    }
                  }
                }
              }
            },
            "radius": {
              "expr": {
                "Literal": {
                  "Value": "8D"
                }
              }
            }
          }
        }
      ],
      "title": [
        {
          "properties": {
            "show": {
              "expr": {
                "Literal": {
                  "Value": "true"
                }
              }
            },
            "text": {
              "expr": {
                "Literal": {
                  "Value": "'City footprint — Icon Map'"
                }
              }
            },
            "fontSize": {
              "expr": {
                "Literal": {
                  "Value": "12D"
                }
              }
            },
            "fontColor": {
              "solid": {
                "color": {
                  "expr": {
                    "Literal": {
                      "Value": "'#0F1C24'"
                    }
                  }
                }
              }
            },
            "fontFamily": {
              "expr": {
                "Literal": {
                  "Value": "'Segoe UI Semibold'"
                }
              }
            }
          }
        }
      ],
      "visualHeader": [
        {
          "properties": {
            "show": {
              "expr": {
                "Literal": {
                  "Value": "false"
                }
              }
            }
          }
        }
      ],
      "padding": [
        {
          "properties": {
            "top": {
              "expr": {
                "Literal": {
                  "Value": "8D"
                }
              }
            },
            "bottom": {
              "expr": {
                "Literal": {
                  "Value": "8D"
                }
              }
            },
            "left": {
              "expr": {
                "Literal": {
                  "Value": "12D"
                }
              }
            },
            "right": {
              "expr": {
                "Literal": {
                  "Value": "12D"
                }
              }
            }
          }
        }
      ]
    }
  }
}